pulumi_scaleway_instances/__init__.py
pulumi_scaleway_instances/_utilities.py
pulumi_scaleway_instances/provider.py
pulumi_scaleway_instances/pulumi-plugin.json
pulumi_scaleway_instances/py.typed
pulumi_scaleway_instances/action/__init__.py
pulumi_scaleway_instances/action/_enums.py
pulumi_scaleway_instances/action/_inputs.py
pulumi_scaleway_instances/action/list_server_actions.py
pulumi_scaleway_instances/action/outputs.py
pulumi_scaleway_instances/action/server_action.py
pulumi_scaleway_instances/availability/__init__.py
pulumi_scaleway_instances/availability/_enums.py
pulumi_scaleway_instances/availability/get_server_types_availability.py
pulumi_scaleway_instances/availability/outputs.py
pulumi_scaleway_instances/bootscripts/__init__.py
pulumi_scaleway_instances/bootscripts/_enums.py
pulumi_scaleway_instances/bootscripts/get_bootscript.py
pulumi_scaleway_instances/bootscripts/list_bootscripts.py
pulumi_scaleway_instances/bootscripts/outputs.py
pulumi_scaleway_instances/config/__init__.py
pulumi_scaleway_instances/config/__init__.pyi
pulumi_scaleway_instances/config/vars.py
pulumi_scaleway_instances/dashboard/__init__.py
pulumi_scaleway_instances/dashboard/get_dashboard.py
pulumi_scaleway_instances/dashboard/outputs.py
pulumi_scaleway_instances/export/__init__.py
pulumi_scaleway_instances/export/_enums.py
pulumi_scaleway_instances/export/export_snapshot.py
pulumi_scaleway_instances/export/outputs.py
pulumi_scaleway_instances/images/__init__.py
pulumi_scaleway_instances/images/_enums.py
pulumi_scaleway_instances/images/_inputs.py
pulumi_scaleway_instances/images/get_image.py
pulumi_scaleway_instances/images/image.py
pulumi_scaleway_instances/images/list_images.py
pulumi_scaleway_instances/images/outputs.py
pulumi_scaleway_instances/ips/__init__.py
pulumi_scaleway_instances/ips/_inputs.py
pulumi_scaleway_instances/ips/get_ip.py
pulumi_scaleway_instances/ips/ip.py
pulumi_scaleway_instances/ips/list_ips.py
pulumi_scaleway_instances/ips/outputs.py
pulumi_scaleway_instances-0.1.4.dist-info/METADATA
pulumi_scaleway_instances-0.1.4.dist-info/WHEEL
pulumi_scaleway_instances-0.1.4.dist-info/top_level.txt
pulumi_scaleway_instances-0.1.4.dist-info/RECORD
