Metadata-Version: 2.1
Name: pulumi_scaleway_instances
Version: 0.1.4
Summary: A Pulumi package for creating and managing Scaleway Instances resources.
License: Apache-2.0
Project-URL: Homepage, https://cloudysky.software
Project-URL: Repository, https://github.com/cloudy-sky-software/pulumi-scaleway-instances
Keywords: pulumi,scaleway-instances,category/cloud,kind/native
Requires-Python: >=3.8
Requires-Dist: parver >=0.2.1
Requires-Dist: pulumi <4.0.0,>=3.0.0
Requires-Dist: semver >=2.8.1
